azureml/__init__.py
azureml/_third_party_notice/ThirdPartyNotice-Widgets.html
azureml/widgets/__init__.py
azureml/widgets/_constants.py
azureml/widgets/_platform.py
azureml/widgets/_telemetry_logger.py
azureml/widgets/_transformer.py
azureml/widgets/_universal_widgets.py
azureml/widgets/_utils.py
azureml/widgets/_widget_run_details_base.py
azureml/widgets/_widgets.py
azureml/widgets/parallel_run_step_details.py
azureml/widgets/run_details.py
azureml/widgets/_automl/__init__.py
azureml/widgets/_automl/_run_details.py
azureml/widgets/_automl/_transformer.py
azureml/widgets/_automl/_universal_widget.py
azureml/widgets/_automl/_widget.py
azureml/widgets/_hyperdrive/__init__.py
azureml/widgets/_hyperdrive/_run_details.py
azureml/widgets/_hyperdrive/_transformer.py
azureml/widgets/_hyperdrive/_universal_widget.py
azureml/widgets/_hyperdrive/_widget.py
azureml/widgets/_parallel_run_step/__init__.py
azureml/widgets/_parallel_run_step/_data_downloader.py
azureml/widgets/_parallel_run_step/_parallel_run_step_visualizer.py
azureml/widgets/_parallel_run_step/_progress_bar.py
azureml/widgets/_pipeline/__init__.py
azureml/widgets/_pipeline/_run_details.py
azureml/widgets/_pipeline/_transformer.py
azureml/widgets/_pipeline/_universal_widget.py
azureml/widgets/_pipeline/_widget.py
azureml/widgets/_rl_run/__init__.py
azureml/widgets/_rl_run/_run_details.py
azureml/widgets/_rl_run/_universal_widget.py
azureml/widgets/_rl_run/_widget.py
azureml/widgets/_userrun/__init__.py
azureml/widgets/_userrun/_run_details.py
azureml/widgets/_userrun/_universal_widget.py
azureml/widgets/_userrun/_widget.py
azureml/widgets/static/extension.js
azureml/widgets/static/index.js
azureml/widgets/static/packages/labextension/azureml_widgets-1.1.0.tgz
azureml_widgets-1.60.0.data/data/etc/jupyter/nbconfig/notebook.d/azureml_widgets.json
azureml_widgets-1.60.0.data/data/share/jupyter/lab/extensions/azureml_widgets-1.1.0.tgz
azureml_widgets-1.60.0.dist-info/licenses/LICENSE.txt
azureml_widgets-1.60.0.dist-info/METADATA
azureml_widgets-1.60.0.dist-info/WHEEL
azureml_widgets-1.60.0.dist-info/top_level.txt
azureml_widgets-1.60.0.dist-info/RECORD
